pypponi/__init__.py
pypponi/helloworld.py
pypponi-0.0.1.dist-info/LICENSE
pypponi-0.0.1.dist-info/METADATA
pypponi-0.0.1.dist-info/WHEEL
pypponi-0.0.1.dist-info/top_level.txt
pypponi-0.0.1.dist-info/RECORD
